{
    "spec": {
        "_tasks": [
            {
                "files_to_write": [
                    {
                        "filename": "FW--Si-structure_optimization",
                        "contents": ""
                    }
                ],
                "_fw_name": "FileWriteTask"
            },
            {
                "structure": {
                    "@module": "pymatgen.core.structure",
                    "@class": "Structure",
                    "charge": null,
                    "lattice": {
                        "matrix": [
                            [
                                5.523145,
                                0.0,
                                3.3819509227383545e-16
                            ],
                            [
                                8.794385361720812e-16,
                                5.468728,
                                3.348630120303753e-16
                            ],
                            [
                                0.0,
                                0.0,
                                5.468728
                            ]
                        ],
                        "a": 5.523145,
                        "b": 5.468728,
                        "c": 5.468728,
                        "alpha": 90.0,
                        "beta": 90.0,
                        "gamma": 90.0,
                        "volume": 165.1806198484466
                    },
                    "sites": [
                        {
                            "species": [
                                {
                                    "element": "Si",
                                    "occu": 1.0
                                }
                            ],
                            "abc": [
                                0.25,
                                0.25,
                                0.25
                            ],
                            "xyz": [
                                1.3807862500000003,
                                1.367182,
                                1.3671820000000001
                            ],
                            "label": "Si",
                            "properties": {}
                        },
                        {
                            "species": [
                                {
                                    "element": "Si",
                                    "occu": 1.0
                                }
                            ],
                            "abc": [
                                0.5,
                                0.5,
                                0.0
                            ],
                            "xyz": [
                                2.7615725000000007,
                                2.734364,
                                3.365290521521054e-16
                            ],
                            "label": "Si",
                            "properties": {}
                        },
                        {
                            "species": [
                                {
                                    "element": "Si",
                                    "occu": 1.0
                                }
                            ],
                            "abc": [
                                0.25,
                                0.75,
                                0.75
                            ],
                            "xyz": [
                                1.3807862500000008,
                                4.101546,
                                4.101546
                            ],
                            "label": "Si",
                            "properties": {}
                        },
                        {
                            "species": [
                                {
                                    "element": "Si",
                                    "occu": 1.0
                                }
                            ],
                            "abc": [
                                0.5,
                                0.0,
                                0.5
                            ],
                            "xyz": [
                                2.7615725,
                                0.0,
                                2.734364
                            ],
                            "label": "Si",
                            "properties": {}
                        },
                        {
                            "species": [
                                {
                                    "element": "Si",
                                    "occu": 1.0
                                }
                            ],
                            "abc": [
                                0.75,
                                0.25,
                                0.75
                            ],
                            "xyz": [
                                4.1423587500000005,
                                1.367182,
                                4.101546
                            ],
                            "label": "Si",
                            "properties": {}
                        },
                        {
                            "species": [
                                {
                                    "element": "Si",
                                    "occu": 1.0
                                }
                            ],
                            "abc": [
                                0.0,
                                0.5,
                                0.5
                            ],
                            "xyz": [
                                4.397192680860406e-16,
                                2.734364,
                                2.734364
                            ],
                            "label": "Si",
                            "properties": {}
                        },
                        {
                            "species": [
                                {
                                    "element": "Si",
                                    "occu": 1.0
                                }
                            ],
                            "abc": [
                                0.75,
                                0.75,
                                0.25
                            ],
                            "xyz": [
                                4.142358750000001,
                                4.101546,
                                1.3671820000000003
                            ],
                            "label": "Si",
                            "properties": {}
                        },
                        {
                            "species": [
                                {
                                    "element": "Si",
                                    "occu": 1.0
                                }
                            ],
                            "abc": [
                                0.0,
                                0.0,
                                0.0
                            ],
                            "xyz": [
                                0.0,
                                0.0,
                                0.0
                            ],
                            "label": "Si",
                            "properties": {}
                        }
                    ]
                },
                "vasp_input_set": {
                    "@module": "pymatgen.io.vasp.sets",
                    "@class": "MPRelaxSet",
                    "@version": null,
                    "structure": {
                        "@module": "pymatgen.core.structure",
                        "@class": "Structure",
                        "charge": null,
                        "lattice": {
                            "matrix": [
                                [
                                    5.523145,
                                    0.0,
                                    3.3819509227383545e-16
                                ],
                                [
                                    8.794385361720812e-16,
                                    5.468728,
                                    3.348630120303753e-16
                                ],
                                [
                                    0.0,
                                    0.0,
                                    5.468728
                                ]
                            ],
                            "a": 5.523145,
                            "b": 5.468728,
                            "c": 5.468728,
                            "alpha": 90.0,
                            "beta": 90.0,
                            "gamma": 90.0,
                            "volume": 165.1806198484466
                        },
                        "sites": [
                            {
                                "species": [
                                    {
                                        "element": "Si",
                                        "occu": 1.0
                                    }
                                ],
                                "abc": [
                                    0.25,
                                    0.25,
                                    0.25
                                ],
                                "xyz": [
                                    1.3807862500000003,
                                    1.367182,
                                    1.3671820000000001
                                ],
                                "label": "Si",
                                "properties": {}
                            },
                            {
                                "species": [
                                    {
                                        "element": "Si",
                                        "occu": 1.0
                                    }
                                ],
                                "abc": [
                                    0.5,
                                    0.5,
                                    0.0
                                ],
                                "xyz": [
                                    2.7615725000000007,
                                    2.734364,
                                    3.365290521521054e-16
                                ],
                                "label": "Si",
                                "properties": {}
                            },
                            {
                                "species": [
                                    {
                                        "element": "Si",
                                        "occu": 1.0
                                    }
                                ],
                                "abc": [
                                    0.25,
                                    0.75,
                                    0.75
                                ],
                                "xyz": [
                                    1.3807862500000008,
                                    4.101546,
                                    4.101546
                                ],
                                "label": "Si",
                                "properties": {}
                            },
                            {
                                "species": [
                                    {
                                        "element": "Si",
                                        "occu": 1.0
                                    }
                                ],
                                "abc": [
                                    0.5,
                                    0.0,
                                    0.5
                                ],
                                "xyz": [
                                    2.7615725,
                                    0.0,
                                    2.734364
                                ],
                                "label": "Si",
                                "properties": {}
                            },
                            {
                                "species": [
                                    {
                                        "element": "Si",
                                        "occu": 1.0
                                    }
                                ],
                                "abc": [
                                    0.75,
                                    0.25,
                                    0.75
                                ],
                                "xyz": [
                                    4.1423587500000005,
                                    1.367182,
                                    4.101546
                                ],
                                "label": "Si",
                                "properties": {}
                            },
                            {
                                "species": [
                                    {
                                        "element": "Si",
                                        "occu": 1.0
                                    }
                                ],
                                "abc": [
                                    0.0,
                                    0.5,
                                    0.5
                                ],
                                "xyz": [
                                    4.397192680860406e-16,
                                    2.734364,
                                    2.734364
                                ],
                                "label": "Si",
                                "properties": {}
                            },
                            {
                                "species": [
                                    {
                                        "element": "Si",
                                        "occu": 1.0
                                    }
                                ],
                                "abc": [
                                    0.75,
                                    0.75,
                                    0.25
                                ],
                                "xyz": [
                                    4.142358750000001,
                                    4.101546,
                                    1.3671820000000003
                                ],
                                "label": "Si",
                                "properties": {}
                            },
                            {
                                "species": [
                                    {
                                        "element": "Si",
                                        "occu": 1.0
                                    }
                                ],
                                "abc": [
                                    0.0,
                                    0.0,
                                    0.0
                                ],
                                "xyz": [
                                    0.0,
                                    0.0,
                                    0.0
                                ],
                                "label": "Si",
                                "properties": {}
                            }
                        ]
                    },
                    "force_gamma": true
                },
                "_fw_name": "{{atomate.vasp.firetasks.write_inputs.WriteVaspFromIOSet}}"
            },
            {
                "ref_dir": "/home/runner/work/workshop/workshop/python_module/mp_workshop/atomate/fake_vasp/Si_structure_opt",
                "params_to_check": [
                    "ISPIN",
                    "ENCUT",
                    "ISMEAR",
                    "SIGMA",
                    "IBRION",
                    "LORBIT",
                    "NBANDS",
                    "LMAXMIX"
                ],
                "check_incar": false,
                "check_kpoints": false,
                "check_poscar": false,
                "check_potcar": false,
                "clear_inputs": true,
                "_fw_name": "{{atomate.vasp.firetasks.run_calc.RunVaspFake}}"
            },
            {
                "name": "structure optimization",
                "_fw_name": "{{atomate.common.firetasks.glue_tasks.PassCalcLocs}}"
            },
            {
                "db_file": ">>db_file<<",
                "additional_fields": {
                    "task_label": "structure optimization"
                },
                "_fw_name": "{{atomate.vasp.firetasks.parse_outputs.VaspToDb}}"
            }
        ]
    },
    "fw_id": 5,
    "created_on": "2021-08-10T02:26:34.328225",
    "updated_on": "2021-08-10T02:26:40.369651",
    "launches": [
        {
            "fworker": {
                "name": "MP_Workshop",
                "category": "",
                "query": "{}",
                "env": {
                    "db_file": "/home/runner/work/workshop/workshop/python_module/mp_workshop/fireworks_config/db.json",
                    "scratch_dir": null,
                    "vasp_cmd": null
                }
            },
            "fw_id": 5,
            "launch_dir": "/home/runner/work/workshop/workshop/workshop/lessons/05_automated_dft/launcher_2021-08-10-02-26-40-362793",
            "host": "fv-az154-255",
            "ip": "10.1.0.91",
            "trackers": [],
            "action": null,
            "state": "RUNNING",
            "state_history": [
                {
                    "state": "RUNNING",
                    "created_on": "2021-08-10T02:26:40.368840",
                    "updated_on": "2021-08-10T02:26:40.368843"
                }
            ],
            "launch_id": 2
        }
    ],
    "state": "RUNNING",
    "name": "Si-structure optimization"
}